{"publisher": "Argonaut Project", "title": "Argonaut Questionnaire", "do-transforms": "false", "sct-edition": "http://snomed.info/sct/731000124108", "license": "CC0-1.0", "defaults": {"CapabilityStatement": {"template-base": "base.html"}, "Questionnaire": {"template-base": "ex.html"}, "OperationDefinition": {"template-base": "base.html"}, "StructureMap": {"profiles": false, "script": false, "template-base": "ex.html", "content": false}, "Any": {"template-format": "format.html", "template-base": "base.html"}, "ValueSet": {"template-base": "base.html"}, "SearchParameter": {"template-base": "base.html"}, "ConceptMap": {"template-base": "base.html"}, "StructureDefinition": {"template-defns": "sd-definitions.html", "template-mappings": "sd-mappings.html", "template-base": "sd.html"}, "CodeSystem": {"template-base": "base.html"}}, "html-template": "html-template.html", "broken-links": "warning", "logging": ["progress"], "extraTemplates": ["mappings"], "swagger": [{"mode": "single", "capabilities": "server"}], "gen-examples": "false", "canonicalBase": "http://fhir.org/guides/argonaut-questionnaire", "mappings": "true", "igtemplate-dir": "/Users/ehaas/Documents/FHIR/IG-Template2/", "source": "ig.xml", "paths": {"temp": "generated_output/temp", "output": "docs", "qa": "generated_output/qa", "specification": "http://hl7.org/fhir/STU3", "pages": ["framework", "source/pages"], "txCache": "generated_output/txCache", "resources": ["source/resources", "source/examples"]}, "spreadsheets": ["Q-profile-spreadsheet.xml", "QR-profile-spreadsheet.xml"], "working-dir": "/Users/ehaas/Documents/FHIR/Argonaut-Questionnaire/", "topofpage": "true", "resources": {"Questionnaire/questionnaire-example-audit": {"base": "Questionnaire-questionnaire-example-audit.html", "source": "AUDIT.json"}, "ValueSet/PHQ-9": {"base": "ValueSet-PHQ-9.html", "source": "ValueSet-phq9.xml"}, "CapabilityStatement/server": {"base": "CapabilityStatement-server.html", "source": "capabilitystatement-server.xml"}, "StructureDefinition/qr": {"defns": "StructureDefinition-qr-definitions.html", "base": "StructureDefinition-qr.html"}, "ValueSet/example-answerlist1": {"base": "ValueSet-example-answerlist1.html", "source": "ValueSet-answerlist1.xml"}, "CapabilityStatement/client": {"base": "CapabilityStatement-client.html", "source": "capabilitystatement-client.xml"}, "ValueSet/SAMHSA-6": {"base": "ValueSet-SAMHSA-6.html", "source": "ValueSet-samhsa-6.xml"}, "CodeSystem/answer-codes": {"base": "CodeSystem-answer-codes.html", "source": "CodeSystem-answer-codes.xml"}, "ValueSet/SAMHSA-dad": {"base": "ValueSet-SAMHSA-dad.html", "source": "ValueSet-samhsa-drinks-a-day.xml"}, "Questionnaire/questionnaire-example-dast": {"base": "Questionnaire-questionnaire-example-dast.html", "source": "DAST.json"}, "Questionnaire/questionnaire-example-asq3": {"base": "Questionnaire-questionnaire-example-asq3.html", "source": "ASQ3.json"}, "Questionnaire/questionnaire-example-phq9": {"base": "Questionnaire-questionnaire-example-phq9.html", "source": "PHQ9.json"}, "StructureDefinition/q": {"defns": "StructureDefinition-q-definitions.html", "base": "StructureDefinition-q.html"}, "Questionnaire/questionnaire-example-housing": {"base": "Questionnaire-questionnaire-example-housing.html", "source": "Housing.json"}}, "status": "draft", "pub_url": "ehaas@healthedatainc.com", "no-inactive-codes": "false", "tool": "jekyll", "fixed-business-version": "0.0.0", "version": "3.0.1", "allviews": "true", "dependencyList": [{"location": "http://hl7.org/fhir/us/core/1.0.1/", "name": "uscore", "source": "dependencies/uscore-vp"}]}